open_buildings/__init__.py
open_buildings/cli.py
open_buildings/common.py
open_buildings/download_buildings.py
open_buildings/google/__init.py__
open_buildings/google/add_columns.py
open_buildings/google/partition.py
open_buildings/google/process.py
open_buildings/google/stac-geoparquet.py
open_buildings/overture/__init.py__
open_buildings/overture/add_columns.py
open_buildings/overture/partition.py
open_buildings/overture/places_add_columns.py
tests/__init__.py
tests/test_open_buildings.py
open_buildings-0.10.0.dist-info/LICENSE
open_buildings-0.10.0.dist-info/METADATA
open_buildings-0.10.0.dist-info/WHEEL
open_buildings-0.10.0.dist-info/dependency_links.txt
open_buildings-0.10.0.dist-info/entry_points.txt
open_buildings-0.10.0.dist-info/top_level.txt
open_buildings-0.10.0.dist-info/RECORD
