Metadata-Version: 2.1
Name: open-buildings
Version: 0.10.0
Summary: Tools for working with open building datasets
Home-page: https://github.com/opengeos/open-buildings
Author: Chris Holmes
Author-email: cholmes@9eo.org
License: Apache Software License 2.0
Keywords: open_buildings
Classifier: Intended Audience :: Developers
Classifier: License :: OSI Approved :: Apache Software License
Classifier: Natural Language :: English
Classifier: Programming Language :: Python :: 3
Classifier: Programming Language :: Python :: 3.8
Classifier: Programming Language :: Python :: 3.9
Classifier: Programming Language :: Python :: 3.10
Classifier: Programming Language :: Python :: 3.11
Requires-Python: >=3.8
License-File: LICENSE
Requires-Dist: click
Requires-Dist: duckdb
Requires-Dist: pandas
Requires-Dist: geopandas
Requires-Dist: shapely
Requires-Dist: openlocationcode
Requires-Dist: tabulate
Requires-Dist: leafmap
Requires-Dist: boto3
Requires-Dist: mercantile
